{
    "/js//main.min.js": "/js//main.min.js",
    "/js//login.min.js": "/js//login.min.js",
    "/js/bundle/dashboard.62015daef116adac.js": "/js/bundle/dashboard.62015daef116adac.js",
    "/js/bundle/products.62015daef116adac.js": "/js/bundle/products.62015daef116adac.js",
    "/js/bundle/index_products.62015daef116adac.js": "/js/bundle/index_products.62015daef116adac.js",
    "/js/bundle/store_product.62015daef116adac.js": "/js/bundle/store_product.62015daef116adac.js",
    "/js/bundle/edit_product.62015daef116adac.js": "/js/bundle/edit_product.62015daef116adac.js",
    "/js/bundle/detail_product.62015daef116adac.js": "/js/bundle/detail_product.62015daef116adac.js",
    "/js/bundle/barcode.62015daef116adac.js": "/js/bundle/barcode.62015daef116adac.js",
    "/js/bundle/Categories.62015daef116adac.js": "/js/bundle/Categories.62015daef116adac.js",
    "/js/bundle/Brands.62015daef116adac.js": "/js/bundle/Brands.62015daef116adac.js",
    "/js/bundle/units.62015daef116adac.js": "/js/bundle/units.62015daef116adac.js",
    "/js/bundle/adjustments.62015daef116adac.js": "/js/bundle/adjustments.62015daef116adac.js",
    "/js/bundle/index_adjustment.62015daef116adac.js": "/js/bundle/index_adjustment.62015daef116adac.js",
    "/js/bundle/store_adjustment.62015daef116adac.js": "/js/bundle/store_adjustment.62015daef116adac.js",
    "/js/bundle/edit_adjustment.62015daef116adac.js": "/js/bundle/edit_adjustment.62015daef116adac.js",
    "/js/bundle/transfers.62015daef116adac.js": "/js/bundle/transfers.62015daef116adac.js",
    "/js/bundle/index_transfer.62015daef116adac.js": "/js/bundle/index_transfer.62015daef116adac.js",
    "/js/bundle/store_transfer.62015daef116adac.js": "/js/bundle/store_transfer.62015daef116adac.js",
    "/js/bundle/edit_transfer.62015daef116adac.js": "/js/bundle/edit_transfer.62015daef116adac.js",
    "/js/bundle/expenses.62015daef116adac.js": "/js/bundle/expenses.62015daef116adac.js",
    "/js/bundle/index_expense.62015daef116adac.js": "/js/bundle/index_expense.62015daef116adac.js",
    "/js/bundle/store_expense.62015daef116adac.js": "/js/bundle/store_expense.62015daef116adac.js",
    "/js/bundle/edit_expense.62015daef116adac.js": "/js/bundle/edit_expense.62015daef116adac.js",
    "/js/bundle/expense_category.62015daef116adac.js": "/js/bundle/expense_category.62015daef116adac.js",
    "/js/bundle/quotations.62015daef116adac.js": "/js/bundle/quotations.62015daef116adac.js",
    "/js/bundle/store_quotation.62015daef116adac.js": "/js/bundle/store_quotation.62015daef116adac.js",
    "/js/bundle/edit_quotation.62015daef116adac.js": "/js/bundle/edit_quotation.62015daef116adac.js",
    "/js/bundle/detail_quotation.62015daef116adac.js": "/js/bundle/detail_quotation.62015daef116adac.js",
    "/js/bundle/change_to_sale.62015daef116adac.js": "/js/bundle/change_to_sale.62015daef116adac.js",
    "/js/bundle/purchases.62015daef116adac.js": "/js/bundle/purchases.62015daef116adac.js",
    "/js/bundle/index_purchases.62015daef116adac.js": "/js/bundle/index_purchases.62015daef116adac.js",
    "/js/bundle/store_purchase.62015daef116adac.js": "/js/bundle/store_purchase.62015daef116adac.js",
    "/js/bundle/edit_purchase.62015daef116adac.js": "/js/bundle/edit_purchase.62015daef116adac.js",
    "/js/bundle/create_purchase_return.62015daef116adac.js": "/js/bundle/create_purchase_return.62015daef116adac.js",
    "/js/bundle/detail_purchase.62015daef116adac.js": "/js/bundle/detail_purchase.62015daef116adac.js",
    "/js/bundle/sales.62015daef116adac.js": "/js/bundle/sales.62015daef116adac.js",
    "/js/bundle/index_sales.62015daef116adac.js": "/js/bundle/index_sales.62015daef116adac.js",
    "/js/bundle/store_sale.62015daef116adac.js": "/js/bundle/store_sale.62015daef116adac.js",
    "/js/bundle/edit_sale.62015daef116adac.js": "/js/bundle/edit_sale.62015daef116adac.js",
    "/js/bundle/create_sale_return.62015daef116adac.js": "/js/bundle/create_sale_return.62015daef116adac.js",
    "/js/bundle/detail_sale.62015daef116adac.js": "/js/bundle/detail_sale.62015daef116adac.js",
    "/js/bundle/shipment.62015daef116adac.js": "/js/bundle/shipment.62015daef116adac.js",
    "/js/bundle/sale_return.62015daef116adac.js": "/js/bundle/sale_return.62015daef116adac.js",
    "/js/bundle/index_sale_return.62015daef116adac.js": "/js/bundle/index_sale_return.62015daef116adac.js",
    "/js/bundle/edit_sale_return.62015daef116adac.js": "/js/bundle/edit_sale_return.62015daef116adac.js",
    "/js/bundle/detail_sale_return.62015daef116adac.js": "/js/bundle/detail_sale_return.62015daef116adac.js",
    "/js/bundle/purchase_return.62015daef116adac.js": "/js/bundle/purchase_return.62015daef116adac.js",
    "/js/bundle/index_purchase_return.62015daef116adac.js": "/js/bundle/index_purchase_return.62015daef116adac.js",
    "/js/bundle/edit_purchase_return.62015daef116adac.js": "/js/bundle/edit_purchase_return.62015daef116adac.js",
    "/js/bundle/detail_purchase_return.62015daef116adac.js": "/js/bundle/detail_purchase_return.62015daef116adac.js",
    "/js/bundle/hrm.62015daef116adac.js": "/js/bundle/hrm.62015daef116adac.js",
    "/js/bundle/employees.62015daef116adac.js": "/js/bundle/employees.62015daef116adac.js",
    "/js/bundle/index_employee.62015daef116adac.js": "/js/bundle/index_employee.62015daef116adac.js",
    "/js/bundle/store_employee.62015daef116adac.js": "/js/bundle/store_employee.62015daef116adac.js",
    "/js/bundle/edit_employee.62015daef116adac.js": "/js/bundle/edit_employee.62015daef116adac.js",
    "/js/bundle/detail_employee.62015daef116adac.js": "/js/bundle/detail_employee.62015daef116adac.js",
    "/js/bundle/company.62015daef116adac.js": "/js/bundle/company.62015daef116adac.js",
    "/js/bundle/departments.62015daef116adac.js": "/js/bundle/departments.62015daef116adac.js",
    "/js/bundle/designations.62015daef116adac.js": "/js/bundle/designations.62015daef116adac.js",
    "/js/bundle/office_shift.62015daef116adac.js": "/js/bundle/office_shift.62015daef116adac.js",
    "/js/bundle/attendance.62015daef116adac.js": "/js/bundle/attendance.62015daef116adac.js",
    "/js/bundle/holidays.62015daef116adac.js": "/js/bundle/holidays.62015daef116adac.js",
    "/js/bundle/leaves.62015daef116adac.js": "/js/bundle/leaves.62015daef116adac.js",
    "/js/bundle/leave_list.62015daef116adac.js": "/js/bundle/leave_list.62015daef116adac.js",
    "/js/bundle/leave_type.62015daef116adac.js": "/js/bundle/leave_type.62015daef116adac.js",
    "/js/bundle/People.62015daef116adac.js": "/js/bundle/People.62015daef116adac.js",
    "/js/bundle/Customers.62015daef116adac.js": "/js/bundle/Customers.62015daef116adac.js",
    "/js/bundle/Suppliers.62015daef116adac.js": "/js/bundle/Suppliers.62015daef116adac.js",
    "/js/bundle/Users.62015daef116adac.js": "/js/bundle/Users.62015daef116adac.js",
    "/js/bundle/settings.62015daef116adac.js": "/js/bundle/settings.62015daef116adac.js",
    "/js/bundle/permissions.62015daef116adac.js": "/js/bundle/permissions.62015daef116adac.js",
    "/js/bundle/groupPermission.62015daef116adac.js": "/js/bundle/groupPermission.62015daef116adac.js",
    "/js/bundle/store_permission.62015daef116adac.js": "/js/bundle/store_permission.62015daef116adac.js",
    "/js/bundle/edit_permission.62015daef116adac.js": "/js/bundle/edit_permission.62015daef116adac.js",
    "/js/bundle/sms_settings.62015daef116adac.js": "/js/bundle/sms_settings.62015daef116adac.js",
    "/js/bundle/pos_settings.62015daef116adac.js": "/js/bundle/pos_settings.62015daef116adac.js",
    "/js/bundle/payment_gateway.62015daef116adac.js": "/js/bundle/payment_gateway.62015daef116adac.js",
    "/js/bundle/mail_settings.62015daef116adac.js": "/js/bundle/mail_settings.62015daef116adac.js",
    "/js/bundle/update_settings.62015daef116adac.js": "/js/bundle/update_settings.62015daef116adac.js",
    "/js/bundle/Currencies.62015daef116adac.js": "/js/bundle/Currencies.62015daef116adac.js",
    "/js/bundle/Backup.62015daef116adac.js": "/js/bundle/Backup.62015daef116adac.js",
    "/js/bundle/Warehouses.62015daef116adac.js": "/js/bundle/Warehouses.62015daef116adac.js",
    "/js/bundle/System_settings.62015daef116adac.js": "/js/bundle/System_settings.62015daef116adac.js",
    "/js/bundle/payments_purchases.62015daef116adac.js": "/js/bundle/payments_purchases.62015daef116adac.js",
    "/js/bundle/payments_sales.62015daef116adac.js": "/js/bundle/payments_sales.62015daef116adac.js",
    "/js/bundle/payments_purchases_returns.62015daef116adac.js": "/js/bundle/payments_purchases_returns.62015daef116adac.js",
    "/js/bundle/payments_sales_returns.62015daef116adac.js": "/js/bundle/payments_sales_returns.62015daef116adac.js",
    "/js/bundle/profit_and_loss.62015daef116adac.js": "/js/bundle/profit_and_loss.62015daef116adac.js",
    "/js/bundle/quantity_alerts.62015daef116adac.js": "/js/bundle/quantity_alerts.62015daef116adac.js",
    "/js/bundle/warehouse_report.62015daef116adac.js": "/js/bundle/warehouse_report.62015daef116adac.js",
    "/js/bundle/sales_report.62015daef116adac.js": "/js/bundle/sales_report.62015daef116adac.js",
    "/js/bundle/product_sales_report.62015daef116adac.js": "/js/bundle/product_sales_report.62015daef116adac.js",
    "/js/bundle/purchase_report.62015daef116adac.js": "/js/bundle/purchase_report.62015daef116adac.js",
    "/js/bundle/product_purchases_report.62015daef116adac.js": "/js/bundle/product_purchases_report.62015daef116adac.js",
    "/js/bundle/customers_report.62015daef116adac.js": "/js/bundle/customers_report.62015daef116adac.js",
    "/js/bundle/detail_customer_report.62015daef116adac.js": "/js/bundle/detail_customer_report.62015daef116adac.js",
    "/js/bundle/providers_report.62015daef116adac.js": "/js/bundle/providers_report.62015daef116adac.js",
    "/js/bundle/detail_supplier_report.62015daef116adac.js": "/js/bundle/detail_supplier_report.62015daef116adac.js",
    "/js/bundle/top_selling_products.62015daef116adac.js": "/js/bundle/top_selling_products.62015daef116adac.js",
    "/js/bundle/product_report.62015daef116adac.js": "/js/bundle/product_report.62015daef116adac.js",
    "/js/bundle/detail_product_report.62015daef116adac.js": "/js/bundle/detail_product_report.62015daef116adac.js",
    "/js/bundle/top_customers.62015daef116adac.js": "/js/bundle/top_customers.62015daef116adac.js",
    "/js/bundle/stock_report.62015daef116adac.js": "/js/bundle/stock_report.62015daef116adac.js",
    "/js/bundle/detail_stock_report.62015daef116adac.js": "/js/bundle/detail_stock_report.62015daef116adac.js",
    "/js/bundle/users_report.62015daef116adac.js": "/js/bundle/users_report.62015daef116adac.js",
    "/js/bundle/detail_user_report.62015daef116adac.js": "/js/bundle/detail_user_report.62015daef116adac.js",
    "/js/bundle/profile.62015daef116adac.js": "/js/bundle/profile.62015daef116adac.js",
    "/js/bundle/pos.62015daef116adac.js": "/js/bundle/pos.62015daef116adac.js",
    "/js/bundle/NotFound.62015daef116adac.js": "/js/bundle/NotFound.62015daef116adac.js",
    "/js/bundle/not_authorize.62015daef116adac.js": "/js/bundle/not_authorize.62015daef116adac.js",
    "/js/bundle/largeSidebar.62015daef116adac.js": "/js/bundle/largeSidebar.62015daef116adac.js",
    "/js/bundle/customizer.62015daef116adac.js": "/js/bundle/customizer.62015daef116adac.js",
    "/js/bundle/vue-perfect-scrollbar.62015daef116adac.js": "/js/bundle/vue-perfect-scrollbar.62015daef116adac.js"
}
